Metadata-Version: 1.0
Name: adventure-game
Version: 1.2
Summary: a type of game
Home-page: UNKNOWN
Author: Paulynn Yu
Author-email: paulynnyu@gmail.com
License: UNKNOWN
Platform: UNKNOWN
